{
  "projects": [
    {
      "id": "emerald-cli",
      "title": "Emerald CLI",
      "description": "Console tool to access blockchain data, manage private keys, sign and send transaction",
      "links": {
        "github": "https://github.com/etcdevteam/emerald-cli"
      }
    },
    {
      "id": "emerald-js",
      "title": "Emerald JS",
      "description": "Javascript utility library and a framework to build Dapps on Ethereum Classic",
      "links": {
        "github": "https://github.com/etcdevteam/emerald-js"
      }
    }
  ]
}
